bybit/__init__.py
bybit/ccxt/__init__.py
bybit/ccxt/bybit.py
bybit/ccxt/abstract/bybit.py
bybit/ccxt/async_support/__init__.py
bybit/ccxt/async_support/bybit.py
bybit/ccxt/async_support/base/__init__.py
bybit/ccxt/async_support/base/exchange.py
bybit/ccxt/async_support/base/throttler.py
bybit/ccxt/async_support/base/ws/__init__.py
bybit/ccxt/async_support/base/ws/cache.py
bybit/ccxt/async_support/base/ws/client.py
bybit/ccxt/async_support/base/ws/functions.py
bybit/ccxt/async_support/base/ws/future.py
bybit/ccxt/async_support/base/ws/order_book.py
bybit/ccxt/async_support/base/ws/order_book_side.py
bybit/ccxt/base/__init__.py
bybit/ccxt/base/decimal_to_precision.py
bybit/ccxt/base/errors.py
bybit/ccxt/base/exchange.py
bybit/ccxt/base/precise.py
bybit/ccxt/base/types.py
bybit/ccxt/pro/__init__.py
bybit/ccxt/pro/bybit.py
bybit/ccxt/static_dependencies/README.md
bybit/ccxt/static_dependencies/__init__.py
bybit/ccxt/static_dependencies/bip/__init__.py
bybit/ccxt/static_dependencies/bip/addr/P2PKH_addr.py
bybit/ccxt/static_dependencies/bip/addr/__init__.py
bybit/ccxt/static_dependencies/bip/addr/addr_dec_utils.py
bybit/ccxt/static_dependencies/bip/addr/addr_key_validator.py
bybit/ccxt/static_dependencies/bip/addr/iaddr_decoder.py
bybit/ccxt/static_dependencies/bip/addr/iaddr_encoder.py
bybit/ccxt/static_dependencies/bip/base58/__init__.py
bybit/ccxt/static_dependencies/bip/base58/base58.py
bybit/ccxt/static_dependencies/bip/base58/base58_ex.py
bybit/ccxt/static_dependencies/bip/base58/base58_xmr.py
bybit/ccxt/static_dependencies/bip/bech32/__init__.py
bybit/ccxt/static_dependencies/bip/bech32/bch_bech32.py
bybit/ccxt/static_dependencies/bip/bech32/bech32.py
bybit/ccxt/static_dependencies/bip/bech32/bech32_base.py
bybit/ccxt/static_dependencies/bip/bech32/bech32_ex.py
bybit/ccxt/static_dependencies/bip/bech32/segwit_bech32.py
bybit/ccxt/static_dependencies/bip/bip32/__init__.py
bybit/ccxt/static_dependencies/bip/bip32/bip32_const.py
bybit_api-0.0.120.dist-info/METADATA
bybit_api-0.0.120.dist-info/WHEEL
bybit_api-0.0.120.dist-info/RECORD
